unitelabs/__init__.py
unitelabs/cli/__init__.py
unitelabs/cli/certificate.py
unitelabs/cli/connector.py
unitelabs/config.py
unitelabs/connector.py
unitelabs/features/core/lock_controller/LockController-v2_0.proto
unitelabs/features/core/lock_controller/LockController-v2_0.sila.xml
unitelabs/features/core/lock_controller/__init__.py
unitelabs/features/core/lock_controller/lock_controller.py
unitelabs/features/core/lock_controller/lock_controller_base.py
unitelabs/features/core/sila_service/SiLAService-v1_0.proto
unitelabs/features/core/sila_service/SiLAService-v1_0.sila.xml
unitelabs/features/core/sila_service/__init__.py
unitelabs/features/core/sila_service/sila_service.py
unitelabs/features/examples/greeting_provider/__init__.py
unitelabs/features/examples/greeting_provider/greeting_provider_base.py
unitelabs/features/examples/timer_provider/__init__.py
unitelabs/features/examples/timer_provider/timer_provider_base.py
unitelabs/features/robot/grip_controller/GripController-v1_0.proto
unitelabs/features/robot/grip_controller/GripController-v1_0.sila.xml
unitelabs/features/robot/grip_controller/__init__.py
unitelabs/features/robot/grip_controller/grip_controller_base.py
unitelabs/features/robot/labware_transfer_manipulator_controller/LabwareTransferManipulatorController-v1_0.proto
unitelabs/features/robot/labware_transfer_manipulator_controller/LabwareTransferManipulatorController-v1_0.sila.xml
unitelabs/features/robot/labware_transfer_manipulator_controller/__init__.py
unitelabs/features/robot/labware_transfer_manipulator_controller/labware_transfer_manipulator_controller_base.py
unitelabs/features/robot/movement_controller/MovementController-v1_0.proto
unitelabs/features/robot/movement_controller/MovementController-v1_0.sila.xml
unitelabs/features/robot/movement_controller/__init__.py
unitelabs/features/robot/movement_controller/movement_controller_base.py
unitelabs/features/test/basic_data_types_test/BasicDataTypesTest-v1_0.proto
unitelabs_connector_framework-0.1.5.dist-info/LICENSE
unitelabs_connector_framework-0.1.5.dist-info/METADATA
unitelabs_connector_framework-0.1.5.dist-info/WHEEL
unitelabs_connector_framework-0.1.5.dist-info/entry_points.txt
unitelabs_connector_framework-0.1.5.dist-info/RECORD
