Metadata-Version: 2.1
Name: unitelabs-connector-framework
Version: 0.1.5
Summary: A framework to build connectors based on the SiLA 2 standard specification.
Home-page: https://unitelabs.ch
License: MIT
Keywords: SiLA 2,laboratory,automation,connectivity
Author: UniteLabs AG
Author-email: developers+connector@unitelabs.ch
Requires-Python: >=3.9,<4.0
Classifier: Development Status :: 4 - Beta
Classifier: Intended Audience :: Developers
Classifier: Intended Audience :: Healthcare Industry
Classifier: Intended Audience :: Science/Research
Classifier: License :: OSI Approved :: MIT License
Classifier: Operating System :: OS Independent
Classifier: Programming Language :: Python :: 3
Classifier: Programming Language :: Python :: 3.9
Classifier: Programming Language :: Python :: 3.10
Classifier: Programming Language :: Python :: 3.11
Classifier: Programming Language :: Python :: 3 :: Only
Classifier: Programming Language :: Python :: 3.7
Classifier: Programming Language :: Python :: 3.8
Classifier: Topic :: Software Development :: Libraries
Requires-Dist: click (==8.1.4)
Requires-Dist: pydantic_settings (==2.0.1)
Requires-Dist: unitelabs-sila (==0.1.3)
Project-URL: Bug Tracker, https://gitlab.com/unitelabs/connector-framework/-/issues
Project-URL: Documentation, https://gitlab.com/unitelabs/connector-framework/-/tree/main/docs/
Project-URL: Repository, https://gitlab.com/unitelabs/connector-framework
